pickle_cacher/__init__.py
pickle_cacher/extra_classes.py
pickle_cacher/pickle_cacher.py
pickle_cacher-0.7.9.dist-info/METADATA
pickle_cacher-0.7.9.dist-info/WHEEL
pickle_cacher-0.7.9.dist-info/top_level.txt
pickle_cacher-0.7.9.dist-info/RECORD
