Metadata-Version: 2.1
Name: pickle-cacher
Version: 0.7.9
Summary: Provides the `cached` decorator
Home-page: UNKNOWN
Author: Bao Wei
Author-email: baowei.ur521@gmail.com
License: MIT
Platform: UNKNOWN
Requires-Python: >=3.7
Requires-Dist: atomic-write-path (>=1.3)
Requires-Dist: wrapt (>=1.12)
